titania_nlp/titania_nlp.py
titania_nlp-0.1.9.dist-info/METADATA
titania_nlp-0.1.9.dist-info/WHEEL
titania_nlp-0.1.9.dist-info/top_level.txt
titania_nlp-0.1.9.dist-info/RECORD
