Metadata-Version: 2.1
Name: titania-nlp
Version: 0.1.9
Summary: Named Entity Recognition package using SpaCy
Home-page: https://github.com/your_username/titania_nlp
Author: Sai Teja Reddy
Author-email: saitejareddy123@gmail.com
License: UNKNOWN
Platform: UNKNOWN
Requires-Python: >=3.6, <4
Requires-Dist: spacy (<4.0.0,>=3.0.0)
Requires-Dist: spacytextblob (>=3.0.1)
